causadb/__init__.py
causadb/__version__.py
causadb/causadb.py
causadb/cli/account.py
causadb/cli/data.py
causadb/cli/main.py
causadb/cli/models.py
causadb/cli/utils.py
causadb/data.py
causadb/examples/__init__.py
causadb/examples/heating.py
causadb/model.py
causadb/plotting.py
causadb/utils.py
causadb-1.12.0.dist-info/LICENSE
causadb-1.12.0.dist-info/METADATA
causadb-1.12.0.dist-info/WHEEL
causadb-1.12.0.dist-info/entry_points.txt
causadb-1.12.0.dist-info/RECORD
